aadbook
