Metadata-Version: 1.1
Name: aadbook
Version: 0.1.1
Summary: AADBook -- Access your Azure AD contacts from the command line
Home-page: https://github.com/iamFIREcracker/aadbook
Author: Matteo Landi
Author-email: matteo@matteolandi.net
License: GPLv3
Download-URL: http://pypi.python.org/pypi/aadbook
Keywords: contacts,azure,active,directory,ad
Platform: UNKNOWN
Classifier: Development Status :: 4 - Beta
Classifier: Environment :: Console
Classifier: Intended Audience :: End Users/Desktop
Classifier: Operating System :: OS Independent
Classifier: Programming Language :: Python
Classifier: Programming Language :: Python :: 2.7
Classifier: Programming Language :: Python :: 3.2
Classifier: License :: OSI Approved :: GNU General Public License (GPL)
Classifier: Topic :: Communications :: Email :: Address Book
